ALU/ALU.v
`ifndef GUARD_ALU_V
`define GUARD_ALU_V

`include "ArithmeticPart.v"
`include "Any32.v"
`include "LogicPart.v"

module ALU (
    a,
    b,
    op,
    out,
    all_zeroes
);

    input [31:0] a;
    input [31:0] b;
    input [3:0] op;

    output [31:0] out;
    output all_zeroes;

    wire [31:0] arithmetic_out;
    wire [31:0] logic_out;
    wire not_all_zeroes;

    ArithmeticPart ap (
        .a(a),
        .b(b),
        .op({op[3], op[1]}),
        .out(arithmetic_out)
    );
    LogicPart lp (
        .a(a),
        .b(b),
        .op(op[1:0]),
        .out(logic_out)
    );

    assign out = op[2] ? logic_out : arithmetic_out;

    Any32 any32 (
        .in(out),
        .out(not_all_zeroes)
    );

    assign all_zeroes = ~not_all_zeroes;

endmodule // ALU

`endif

bad_ALU.v
`timescale 1ns / 1ps
//////////////////////////////////////////////////////////////////////////////////
// Description:    This is a poor attempt at writing an ALU
// Dependencies:
//
// Revision:
// Revision 0.01 - File Created
// Additional Comments:
//
//////////////////////////////////////////////////////////////////////////////////

module bad_ALU(
	input [31:0] a, b,
	input	[3:0] aluop,
	output [31:0] result,
	output zero
	);

   reg [31:0]		slt;
   reg [31:0]		logicsel;

   reg [31:0]		alu_val;					// we need to declare this reg
   reg [31:0]		diff;
   wire				ss0;
   wire 				ss1;
   wire 				ss2;
   wire 				ss3;

	assign {ss0,ss1,ss2,ss3} = aluop;	// make assigns

   // define the logicfunction
    always @ ( * )
    begin
        if (ss2 == 0)
            if (ss3 == 0)
                logicsel = a & b;
            else
                logicsel = a | b;
        else
            if (ss3 == 1)
                logicsel= ~(a | b);
            else
                logicsel = a ^ b;
     end

	// always @ ( aluop , a, b )
    // I'm not sure why the original wasn't working, but changing it to this
    // fixes it
	always @ ( * )
		if (aluop == 4'b1010)
		begin
			diff <= a - b;			// calculate the difference
			slt <= 0;				// default value
			if (diff[31] == 1)
				slt <= 32'hFFFFFFFF;  // if MSB is 1 slt is 1
		end

	always @ ( * )
	begin
		case (aluop)
			4'b0000 : alu_val = a + b;
			4'b0010 : alu_val = a - b;
			4'b1010 : alu_val = slt;
			default : alu_val = logicsel;
		endcase
	end

	assign result = alu_val;
	assign zero = (alu_val == 32'b0) ? 1 : 0;

endmodule

ALU/Any2.v
`ifndef GUARD_ANY2_V
`define GUARD_ANY2_V

module Any2 (
    in,
    out
);

    input [1:0] in;
    output out;

    assign out = in[0] | in[1];

endmodule // Any2

`endif

ALU/Any4.v
`ifndef GUARD_ANY4_CPP
`define GUARD_ANY4_CPP

`include "Any2.v"

module Any4 (
    in,
    out
);

    input [3:0] in;
    output out;

    wire r0;
    wire r1;

    Any2 any0 (
        .in(in[1:0]),
        .out(r0)
    );
    Any2 any1 (
        .in(in[3:2]),
        .out(r1)
    );

    assign out = r0 | r1;

endmodule // Any4

`endif

ALU/Any8.v
`ifndef GUARD_ANY4_V
`define GUARD_ANY4_V

`include "Any4.v"

module Any8 (
    in,
    out
);

    input [7:0] in;
    output out;

    wire r0;
    wire r1;

    Any4 any0 (
        .in(in[3:0]),
        .out(r0)
    );
    Any4 any1 (
        .in(in[7:4]),
        .out(r1)
    );

    assign out = r0 | r1;

endmodule // Any8

`endif

ALU/Any16.v
`ifndef GUARD_ANY16_V
`define GUARD_ANY16_V

`include "Any8.v"

module Any16 (
    in,
    out
);

    input [15:0] in;
    output out;

    wire r0;
    wire r1;

    Any8 any0 (
        .in(in[7:0]),
        .out(r0)
    );
    Any8 any1 (
        .in(in[15:8]),
        .out(r1)
    );

    assign out = r0 | r1;

endmodule // Any16

`endif

ALU/Any32.v
`ifndef GUARD_ANY32_V
`define GUARD_ANY32_V

`include "Any16.v"

module Any32 (
    in,
    out
);

    input [31:0] in;
    output out;

    wire r0;
    wire r1;

    Any16 any0 (
        .in(in[15:0]),
        .out(r0)
    );
    Any16 any1 (
        .in(in[31:16]),
        .out(r1)
    );

    assign out = r0 | r1;

endmodule // Any32

`endif

ALU_test.v
// `include "ALU/ALU.v"
`include "Any32.v"
`include "bad_ALU.v"
`timescale 1ns / 1ps

////////////////////////////////////////////////////////////////////////////////
// Tool versions:
// Description: Simple testbench to test the ALU
//
//
// Dependencies:
//
// Revision:
// Revision 0.01 - File Created
// Additional Comments:
//
////////////////////////////////////////////////////////////////////////////////

module ALU_test;

    // Inputs
    reg [31:0] a;
    reg [31:0] b;
    reg [3:0] aluop;

    // Outputs
    wire [31:0] result;
    wire zero;

    // Test clock
    reg clk; // in this version we do not really need the clock

    // Expected outputs
    reg [31:0] exp_result;
    wire exp_zero;
    wire not_exp_zero;

    // Vector and Error counts
    reg [10:0] vec_cnt, err_cnt;

    // TO DO:
    // Define an array called 'testvec' that is wide enough to hold the inputs:
    //   aluop, a, b
    // and the expected output
    //   exp_result
    // for each testcase.
    // Note: we will not store 'exp_zero' in this array.
    reg [99:0] testvec[0:11];

    // The test clock generation
    always  // process always triggers
    begin
        clk=1; #50;  // clk is 1 for 50 ns
        clk=0; #50;  // clk is 0 for 50 ns
    end  // generate a 100 ns clock

    // Initialization
    initial
    begin
        // TO DO:
        // Read the content of the file testvectors_hex.txt into the
        // array testvec. The file contains values in hexadecimal format
        $readmemh("testvectors_hex.txt", testvec);

        err_cnt=0; // number of errors
        vec_cnt=0; // number of vectors
    end

    // TO DO:
    // calculate the value of 'exp_zero' from the 'exp_result'
    Any32 nez (
        .in(exp_result),
        .out(not_exp_zero)
    );
    assign exp_zero = ~not_exp_zero;

    // Tests
    always @ (posedge clk)  // trigger with the test clock
    begin
        // Wait 20 ns, so that we can safely apply the inputs
        #20;

        // Assign the signals from the testvec array
        {aluop,a,b,exp_result}= testvec[vec_cnt];

        // Wait another 60ns after which we will be at 80ns
        #60;

        // Check if output is not what we expect to see
        if ((result !== exp_result) | (zero !== exp_zero))
        begin
            // Display message
            $display("Error at %5d ns: Aluop=%b\ta=%h\tb=%h", $time, aluop,a,b);  // %h displays hex
            $display("       %h (%h expected)",result,exp_result);
            $display(" Zero: %b (%b expected)",zero,exp_zero);  // %b displays binary
            err_cnt = err_cnt + 1;  // increment error count
        end

        vec_cnt = vec_cnt + 1;  // next vector

        // We use === so that we can also test for X
        if ((testvec[vec_cnt][99:96] === 4'bxxxx))
        begin
            // End of test, no more entries...
            $display ("%d tests completed with %d errors", vec_cnt, err_cnt);

            // Wait so that we can see the last result
            #20;

            // Terminate simulation
            $finish;
        end
    end

    initial begin
        $dumpfile("ALU_test_wave.vcd");
        $dumpvars;
    end

    // TO DO:
    // Instantiate the Unit Under Test (UUT)
    // ALU DUT (
    //     .a(a),
    //     .b(b),
    //     .op(aluop),
    //     .out(result),
    //     .all_zeroes(zero)
    // );

    bad_ALU DUT (
        .a(a),
        .b(b),
        .aluop(aluop),
        .result(result),
        .zero(zero)
    );

endmodule

bad_ALU_wave.vcd
$date
	Thu Oct  3 07:06:24 2019
$end
$version
	Icarus Verilog
$end
$timescale
	1ps
$end
$scope module ALU_test $end
$var wire 1 ! exp_zero $end
$var wire 1 " zero $end
$var wire 32 # result [31:0] $end
$var wire 1 $ not_exp_zero $end
$var reg 32 % a [31:0] $end
$var reg 4 & aluop [3:0] $end
$var reg 32 ' b [31:0] $end
$var reg 1 ( clk $end
$var reg 11 ) err_cnt [10:0] $end
$var reg 32 * exp_result [31:0] $end
$var reg 11 + vec_cnt [10:0] $end
$scope module DUT $end
$var wire 32 , a [31:0] $end
$var wire 4 - aluop [3:0] $end
$var wire 32 . b [31:0] $end
$var wire 32 / result [31:0] $end
$var wire 1 " zero $end
$var wire 1 0 ss3 $end
$var wire 1 1 ss2 $end
$var wire 1 2 ss1 $end
$var wire 1 3 ss0 $end
$var reg 32 4 alu_val [31:0] $end
$var reg 32 5 diff [31:0] $end
$var reg 32 6 logicsel [31:0] $end
$var reg 32 7 slt [31:0] $end
$upscope $end
$scope module nez $end
$var wire 32 8 in [31:0] $end
$var wire 1 $ out $end
$var wire 1 9 r1 $end
$var wire 1 : r0 $end
$scope module any0 $end
$var wire 16 ; in [15:0] $end
$var wire 1 : out $end
$var wire 1 < r1 $end
$var wire 1 = r0 $end
$scope module any0 $end
$var wire 8 > in [7:0] $end
$var wire 1 = out $end
$var wire 1 ? r1 $end
$var wire 1 @ r0 $end
$scope module any0 $end
$var wire 4 A in [3:0] $end
$var wire 1 @ out $end
$var wire 1 B r1 $end
$var wire 1 C r0 $end
$scope module any0 $end
$var wire 2 D in [1:0] $end
$var wire 1 C out $end
$upscope $end
$scope module any1 $end
$var wire 2 E in [1:0] $end
$var wire 1 B out $end
$upscope $end
$upscope $end
$scope module any1 $end
$var wire 4 F in [3:0] $end
$var wire 1 ? out $end
$var wire 1 G r1 $end
$var wire 1 H r0 $end
$scope module any0 $end
$var wire 2 I in [1:0] $end
$var wire 1 H out $end
$upscope $end
$scope module any1 $end
$var wire 2 J in [1:0] $end
$var wire 1 G out $end
$upscope $end
$upscope $end
$upscope $end
$scope module any1 $end
$var wire 8 K in [7:0] $end
$var wire 1 < out $end
$var wire 1 L r1 $end
$var wire 1 M r0 $end
$scope module any0 $end
$var wire 4 N in [3:0] $end
$var wire 1 M out $end
$var wire 1 O r1 $end
$var wire 1 P r0 $end
$scope module any0 $end
$var wire 2 Q in [1:0] $end
$var wire 1 P out $end
$upscope $end
$scope module any1 $end
$var wire 2 R in [1:0] $end
$var wire 1 O out $end
$upscope $end
$upscope $end
$scope module any1 $end
$var wire 4 S in [3:0] $end
$var wire 1 L out $end
$var wire 1 T r1 $end
$var wire 1 U r0 $end
$scope module any0 $end
$var wire 2 V in [1:0] $end
$var wire 1 U out $end
$upscope $end
$scope module any1 $end
$var wire 2 W in [1:0] $end
$var wire 1 T out $end
$upscope $end
$upscope $end
$upscope $end
$upscope $end
$scope module any1 $end
$var wire 16 X in [15:0] $end
$var wire 1 9 out $end
$var wire 1 Y r1 $end
$var wire 1 Z r0 $end
$scope module any0 $end
$var wire 8 [ in [7:0] $end
$var wire 1 Z out $end
$var wire 1 \ r1 $end
$var wire 1 ] r0 $end
$scope module any0 $end
$var wire 4 ^ in [3:0] $end
$var wire 1 ] out $end
$var wire 1 _ r1 $end
$var wire 1 ` r0 $end
$scope module any0 $end
$var wire 2 a in [1:0] $end
$var wire 1 ` out $end
$upscope $end
$scope module any1 $end
$var wire 2 b in [1:0] $end
$var wire 1 _ out $end
$upscope $end
$upscope $end
$scope module any1 $end
$var wire 4 c in [3:0] $end
$var wire 1 \ out $end
$var wire 1 d r1 $end
$var wire 1 e r0 $end
$scope module any0 $end
$var wire 2 f in [1:0] $end
$var wire 1 e out $end
$upscope $end
$scope module any1 $end
$var wire 2 g in [1:0] $end
$var wire 1 d out $end
$upscope $end
$upscope $end
$upscope $end
$scope module any1 $end
$var wire 8 h in [7:0] $end
$var wire 1 Y out $end
$var wire 1 i r1 $end
$var wire 1 j r0 $end
$scope module any0 $end
$var wire 4 k in [3:0] $end
$var wire 1 j out $end
$var wire 1 l r1 $end
$var wire 1 m r0 $end
$scope module any0 $end
$var wire 2 n in [1:0] $end
$var wire 1 m out $end
$upscope $end
$scope module any1 $end
$var wire 2 o in [1:0] $end
$var wire 1 l out $end
$upscope $end
$upscope $end
$scope module any1 $end
$var wire 4 p in [3:0] $end
$var wire 1 i out $end
$var wire 1 q r1 $end
$var wire 1 r r0 $end
$scope module any0 $end
$var wire 2 s in [1:0] $end
$var wire 1 r out $end
$upscope $end
$scope module any1 $end
$var wire 2 t in [1:0] $end
$var wire 1 q out $end
$upscope $end
$upscope $end
$upscope $end
$upscope $end
$upscope $end
$upscope $end
$enddefinitions $end
#0
$dumpvars
bx t
bx s
xr
xq
bx p
bx o
bx n
xm
xl
bx k
xj
xi
bx h
bx g
bx f
xe
xd
bx c
bx b
bx a
x`
x_
bx ^
x]
x\
bx [
xZ
xY
bx X
bx W
bx V
xU
xT
bx S
bx R
bx Q
xP
xO
bx N
xM
xL
bx K
bx J
bx I
xH
xG
bx F
bx E
bx D
xC
xB
bx A
x@
x?
bx >
x=
x<
bx ;
x:
x9
bx 8
bx 7
bx 6
bx 5
bx 4
x3
x2
x1
x0
bx /
bx .
bx -
bx ,
b0 +
bx *
b0 )
1(
bx '
bx &
bx %
x$
bx #
x"
x!
$end
#50000
0(
#100000
1(
#120000
1!
0$
0:
09
0=
0<
0Z
0Y
0@
0?
0M
0L
0]
0\
0j
0i
0C
0B
0H
0G
0P
0O
0U
0T
0`
0_
0e
0d
0m
0l
0r
0q
b0 D
b0 E
b0 I
b0 J
b0 Q
b0 R
b0 V
b0 W
b0 a
b0 b
b0 f
b0 g
b0 n
b0 o
b0 s
b0 t
1"
b0 A
b0 F
b0 N
b0 S
b0 ^
b0 c
b0 k
b0 p
b0 >
b0 K
b0 [
b0 h
03
02
01
00
b0 #
b0 /
b0 4
b0 6
b0 ;
b0 X
b0 &
b0 -
b0 %
b0 ,
b0 '
b0 .
b0 *
b0 8
#150000
0(
#180000
b1 +
#200000
1(
#220000
0!
1$
1:
1=
1@
1C
b1 D
0"
b1 A
b1 >
b1 #
b1 /
b1 4
b1 ;
b1 %
b1 ,
b1 *
b1 8
#250000
0(
#280000
b10 +
#300000
1(
#320000
1!
0$
0:
0=
0@
0C
b0 D
1"
b0 A
b0 >
b0 #
b0 /
b0 4
b1 6
b0 ;
b11111111111111111111111111111111 '
b11111111111111111111111111111111 .
b0 *
b0 8
#350000
0(
#380000
b11 +
#400000
1(
#420000
0!
1$
1:
19
1=
1<
1Z
1Y
1@
1?
1M
1L
1]
1\
1j
1i
1C
1B
1H
1G
1P
1O
1U
1T
1`
1_
1e
1d
1m
1l
1r
1q
b11 D
b11 E
b11 I
b11 J
b11 Q
b11 R
b11 V
b11 W
b11 a
b11 b
b11 f
b11 g
b11 n
b11 o
b11 s
b11 t
0"
b1111 A
b1111 F
b1111 N
b1111 S
b1111 ^
b1111 c
b1111 k
b1111 p
b11111111 >
b11111111 K
b11111111 [
b11111111 h
11
b11111111111111111111111111111111 #
b11111111111111111111111111111111 /
b11111111111111111111111111111111 4
b1 6
b1111111111111111 ;
b1111111111111111 X
b10 &
b10 -
b0 %
b0 ,
b1 '
b1 .
b11111111111111111111111111111111 *
b11111111111111111111111111111111 8
#450000
0(
#480000
b100 +
#500000
1(
#520000
0i
0U
0_
0d
0l
0r
0q
b1 E
b10 I
b1 J
b1 Q
b1 R
b0 V
b1 W
b0 b
b10 f
b0 g
b1 n
b0 o
b0 s
b0 t
b111 A
b110 F
b101 N
b100 S
b11 ^
b10 c
b1 k
b0 p
b1100111 >
b1000101 K
b100011 [
b1 h
12
01
b1001000110100010101100111 #
b1001000110100010101100111 /
b1001000110100010101100111 4
b1001000110100010101100111 6
b100010101100111 ;
b100100011 X
b100 &
b100 -
b1001000110100010101100111 %
b1001000110100010101100111 ,
b10001001101010111100110111101111 '
b10001001101010111100110111101111 .
b1001000110100010101100111 *
b1001000110100010101100111 8
#550000
0(
#580000
b101 +
#600000
1(
#620000
1i
1_
1d
1l
1q
b11 E
b11 J
b11 R
b11 W
b10 b
b10 g
b10 o
b10 t
b10001001101010111100110111101111 #
b10001001101010111100110111101111 /
b10001001101010111100110111101111 4
b1111 A
b1110 F
b1101 N
b1100 S
b1011 ^
b1010 c
b1001 k
b1000 p
b10001001101010111100110111101111 6
b11101111 >
b11001101 K
b10101011 [
b10001001 h
10
b1100110111101111 ;
b1000100110101011 X
b101 &
b101 -
b10001001101010111100110111101111 *
b10001001101010111100110111101111 8
#650000
0(
#680000
b110 +
#700000
1(
#720000
0C
0H
0P
0`
0e
0m
b0 D
b10 E
b0 I
b10 J
b0 Q
b10 R
b10 W
b0 a
b0 f
b0 n
b10001000100010001000100010001000 #
b10001000100010001000100010001000 /
b10001000100010001000100010001000 4
b1000 A
b1000 F
b1000 N
b1000 S
b1000 ^
b1000 c
b1000 k
b10001000100010001000100010001000 6
b10001000 >
b10001000 K
b10001000 [
b10001000 h
11
00
b1000100010001000 ;
b1000100010001000 X
b110 &
b110 -
b10001000100010001000100010001000 *
b10001000100010001000100010001000 8
#750000
0(
#780000
b111 +
#800000
1(
#820000
0i
1H
1P
1U
0T
1`
1e
1m
0q
b11 I
b1 J
b10 Q
b11 R
b1 V
b0 W
b10 a
b1 f
b1 g
b11 n
b11 o
b0 t
b111 F
b1110 N
b1 S
b1010 ^
b101 c
b1111 k
b0 p
b1111000 >
b11110 K
b1011010 [
b1111 h
10
b1111010110100001111001111000 #
b1111010110100001111001111000 /
b1111010110100001111001111000 4
b1111010110100001111001111000 6
b1111001111000 ;
b111101011010 X
b111 &
b111 -
b0 %
b0 ,
b11110000101001011110000110000111 '
b11110000101001011110000110000111 .
b1111010110100001111001111000 *
b1111010110100001111001111000 8
#850000
0(
#880000
b1000 +
#900000
1(
#920000
b0 7
b100010001 5
1!
0$
0:
09
0=
0<
0Z
0Y
0@
0?
0M
0L
0]
0\
0j
0B
0H
0G
0P
0O
0U
0`
0_
0e
0d
0m
0l
b0 E
b0 I
b0 J
b0 Q
b0 R
b0 V
b0 a
b0 b
b0 f
b0 g
b0 n
b0 o
1"
b0 A
b0 F
b0 N
b0 S
b0 ^
b0 c
b0 k
b0 >
b0 K
b0 [
b0 h
13
02
00
b0 #
b0 /
b0 4
b11111111111111111111111011101111 6
b0 ;
b0 X
b1010 &
b1010 -
b100000000 %
b100000000 ,
b11111111111111111111111111101111 '
b11111111111111111111111111101111 .
b0 *
b0 8
#950000
0(
#980000
b1001 +
#1000000
1(
#1020000
0"
b11111111111111111111111111111111 #
b11111111111111111111111111111111 /
b11111111111111111111111111111111 4
b11111111111111111111111111111111 7
b11111111111111111111000100000000 5
0!
1$
1:
19
1=
1<
1Z
1Y
1@
1?
1M
1L
1]
1\
1j
1i
1C
1B
1H
1G
1P
1O
1U
1T
1`
1_
1e
1d
1m
1l
1r
1q
b11 D
b11 E
b11 I
b11 J
b11 Q
b11 R
b11 V
b11 W
b11 a
b11 b
b11 f
b11 g
b11 n
b11 o
b11 s
b11 t
b1111 A
b1111 F
b1111 N
b1111 S
b1111 ^
b1111 c
b1111 k
b1111 p
b11111111 >
b11111111 K
b11111111 [
b11111111 h
b1000100000000 6
b1111111111111111 ;
b1111111111111111 X
b1000000000000 '
b1000000000000 .
b11111111111111111111111111111111 *
b11111111111111111111111111111111 8
#1050000
0(
#1080000
b1010 +
#1100000
1(
#1120000
1"
b0 #
b0 /
b0 4
b0 7
b0 5
1!
0$
0:
09
0=
0<
0Z
0Y
0@
0?
0M
0L
0]
0\
0j
0i
0C
0B
0H
0G
0P
0O
0U
0T
0`
0_
0e
0d
0m
0l
0r
0q
b0 D
b0 E
b0 I
b0 J
b0 Q
b0 R
b0 V
b0 W
b0 a
b0 b
b0 f
b0 g
b0 n
b0 o
b0 s
b0 t
b0 A
b0 F
b0 N
b0 S
b0 ^
b0 c
b0 k
b0 p
b0 >
b0 K
b0 [
b0 h
b0 6
b0 ;
b0 X
b100000000 '
b100000000 .
b0 *
b0 8
#1150000
0(
#1180000
b1011 +
#1200000
1(
#1220000
b11111111 5
b11111111 6
b111111111 %
b111111111 ,
#1250000
0(
#1280000
b1100 +
